nonebot_plugin_ayaka_scan_cmd.py
nonebot_plugin_ayaka_scan_cmd-0.2.0.dist-info/LICENSE
nonebot_plugin_ayaka_scan_cmd-0.2.0.dist-info/METADATA
nonebot_plugin_ayaka_scan_cmd-0.2.0.dist-info/WHEEL
nonebot_plugin_ayaka_scan_cmd-0.2.0.dist-info/RECORD
