Metadata-Version: 2.1
Name: nonebot-plugin-ayaka-scan-cmd
Version: 0.2.0
Summary: 扫描当前所有matcher，总结命令
Home-page: https://github.com/bridgeL/nonebot-plugin-ayaka-scan-cmd
License: MIT
Author: Su
Author-email: wxlxy316@163.com
Requires-Python: >=3.10,<4.0
Classifier: License :: OSI Approved :: MIT License
Classifier: Programming Language :: Python :: 3
Classifier: Programming Language :: Python :: 3.10
Classifier: Programming Language :: Python :: 3.11
Requires-Dist: ayaka[nb2ob11] (>=0.0.4.2b1,<0.0.5.0)
Project-URL: Repository, https://github.com/bridgeL/nonebot-plugin-ayaka-scan-cmd
